{"response": {"DataHoraDestino": "14-10-2023 21:58:00", "DataHoraOrigem": "14-10-2023 16:00:00", "Destino": "PORTO-CAMPANH\u00c3", "DuracaoViagem": "05:58", "NodesPassagemComboio": [{"ComboioPassou": true, "HoraProgramada": "16:00", "NodeID": 9473007, "NomeEstacao": "FARO", "Observacoes": ""}, {"ComboioPassou": true, "HoraProgramada": "16:09", "NodeID": 9478238, "NomeEstacao": "LOUL\u00c9", "Observacoes": ""}, {"ComboioPassou": true, "HoraProgramada": "16:22", "NodeID": 9478063, "NomeEstacao": "ALBUFEIRA", "Observacoes": ""}, {"ComboioPassou": true, "HoraProgramada": "16:28", "NodeID": 9478006, "NomeEstacao": "TUNES", "Observacoes": ""}, {"ComboioPassou": true, "HoraProgramada": "18:22", "NodeID": 9468007, "NomeEstacao": "PINHAL NOVO", "Observacoes": "Hora Prevista:18:36"}, {"ComboioPassou": true, "HoraProgramada": "18:56", "NodeID": 9466050, "NomeEstacao": "ENTRECAMPOS", "Observacoes": ""}, {"ComboioPassou": true, "HoraProgramada": "19:05", "NodeID": 9431039, "NomeEstacao": "LISBOA-ORIENTE", "Observacoes": ""}, {"ComboioPassou": false, "HoraProgramada": "20:42", "NodeID": 9436004, "NomeEstacao": "COIMBRA-B", "Observacoes": "Hora Prevista:20:49"}, {"ComboioPassou": false, "HoraProgramada": "21:09", "NodeID": 9438000, "NomeEstacao": "AVEIRO", "Observacoes": "Hora Prevista:21:15"}, {"ComboioPassou": false, "HoraProgramada": "21:46", "NodeID": 9439164, "NomeEstacao": "GAIA-DEVESAS", "Observacoes": "Hora Prevista:21:53"}, {"ComboioPassou": false, "HoraProgramada": "21:58", "NodeID": 9402006, "NomeEstacao": "PORTO-CAMPANH\u00c3", "Observacoes": "Hora Prevista:22:04"}], "Operador": "CP LONGO CURSO", "Origem": "FARO", "SituacaoComboio": "Programado", "TipoServico": "ALFA"}}